a2conf/__init__.py
a2conf-0.3.5.dist-info/METADATA
a2conf-0.3.5.dist-info/WHEEL
a2conf-0.3.5.dist-info/top_level.txt
a2conf-0.3.5.dist-info/RECORD
