Metadata-Version: 2.1
Name: a2conf
Version: 0.3.5
Summary: apache2 configuration file parser and query tool
Home-page: https://github.com/yaroslaff/a2conf
Author: Yaroslav Polyakov
Author-email: yaroslaff@gmail.com
License: MIT
Classifier: Development Status :: 3 - Alpha
Classifier: Intended Audience :: Developers
Classifier: License :: OSI Approved :: MIT License
Requires-Python: >=3
Requires-Dist: requests
